slidingpuzzle/__about__.py
slidingpuzzle/__init__.py
slidingpuzzle/algorithms.py
slidingpuzzle/board.py
slidingpuzzle/heuristics.py
slidingpuzzle/state.py
slidingpuzzle/nn/__init__.py
slidingpuzzle/nn/dataset.py
slidingpuzzle/nn/eval.py
slidingpuzzle/nn/heuristics.py
slidingpuzzle/nn/models.py
slidingpuzzle/nn/paths.py
slidingpuzzle/nn/train.py
slidingpuzzle-0.1.5.dist-info/METADATA
slidingpuzzle-0.1.5.dist-info/WHEEL
slidingpuzzle-0.1.5.dist-info/licenses/LICENSE
slidingpuzzle-0.1.5.dist-info/RECORD
