Metadata-Version: 2.1
Name: slidingpuzzle
Version: 0.1.5
Summary: Sliding Puzzle solver
Project-URL: Homepage, https://github.com/entangledloops/slidingpuzzle
Project-URL: Bug Tracker, https://github.com/entangledloops/slidingpuzzle/issues
Author-email: Stephen Dunn <dunn.stephen@gmail.com>
License-File: LICENSE
Classifier: Development Status :: 3 - Alpha
Classifier: License :: OSI Approved :: Apache Software License
Classifier: Operating System :: OS Independent
Classifier: Programming Language :: Python :: 3
Classifier: Programming Language :: Python :: 3.10
Requires-Python: >=3.10
Requires-Dist: numpy==1.23.5
